SajadEnc/__init__.py
SajadNewEnc-1.dist-info/METADATA
SajadNewEnc-1.dist-info/WHEEL
SajadNewEnc-1.dist-info/top_level.txt
SajadNewEnc-1.dist-info/RECORD
