Metadata-Version: 2.1
Name: SajadNewEnc
Version: 1
Summary: an encryption library for sajad
Author: SajadNewEnc
Classifier: Programming Language :: Python :: 3
